aws_tools/dynamodb_handler.py
aws_tools/s3_handler.py
aws_tools/__init__.py
client/client_callback.py
client/preprocessors.py
client/__init__.py
client/client_webhook.py
resource_container/ResourceContainer.py
resource_container/__init__.py
converters/usfm2html_converter.py
converters/converter.py
converters/md2html_converter.py
converters/convert_logger.py
converters/__init__.py
converters/templates/obs-template.html
converters/templates/template.html
converters/templates/bible-template.html
gogs_tools/gogs_handler.py
gogs_tools/__init__.py
tx_manager-0.2.64.dist-info/DESCRIPTION.rst
tx_manager-0.2.64.dist-info/RECORD
tx_manager-0.2.64.dist-info/METADATA
tx_manager-0.2.64.dist-info/metadata.json
tx_manager-0.2.64.dist-info/WHEEL
tx_manager-0.2.64.dist-info/top_level.txt
door43_tools/templaters.py
door43_tools/obs_data.py
door43_tools/project_printer.py
door43_tools/td_language.py
door43_tools/obs_handler.py
door43_tools/bible_books.py
door43_tools/__init__.py
door43_tools/project_deployer.py
manager/module.py
manager/manager.py
manager/object.py
manager/job.py
manager/__init__.py
lambda_handlers/door43_print_handler.py
lambda_handlers/list_endpoints_handler.py
lambda_handlers/client_callback_handler.py
lambda_handlers/dashboard_handler.py
lambda_handlers/start_job_handler.py
lambda_handlers/list_jobs_handler.py
lambda_handlers/convert_handler.py
lambda_handlers/request_job_handler.py
lambda_handlers/door43_deploy_handler.py
lambda_handlers/client_webhook_handler.py
lambda_handlers/register_module_handler.py
lambda_handlers/handler.py
lambda_handlers/__init__.py
general_tools/print_utils.py
general_tools/smartquotes.py
general_tools/url_utils.py
general_tools/file_utils.py
general_tools/__init__.py
