Metadata-Version: 2.0
Name: tx-manager
Version: 0.2.64
Summary: Classes for executing tX Manager
Home-page: https://github.org/unfoldingWord-dev/tx-manager
Author: unfoldingWord
Author-email: info@unfoldingword.org
License: MIT
Keywords: tX manager,unfoldingword,usfm,md2html,usfm2html
Platform: UNKNOWN
Classifier: License :: OSI Approved :: MIT License
Classifier: Programming Language :: Python :: 2.7
Requires-Dist: requests (==2.13.0)
Requires-Dist: responses (==0.5.1)
Requires-Dist: gogs-client (==1.0.3)
Requires-Dist: bs4 (==0.0.1)
Requires-Dist: boto3 (==1.4.4)
Requires-Dist: python-json-logger (==0.1.5)
Requires-Dist: markdown (==2.6.8)
Requires-Dist: future (==0.16.0)
Requires-Dist: pyparsing (==2.1.10)
Requires-Dist: usfm-tools (==0.0.12)
Requires-Dist: PyYAML (==3.12)
